econfiguration/__init__.py
econfiguration-0.5.3.dist-info/METADATA
econfiguration-0.5.3.dist-info/WHEEL
econfiguration-0.5.3.dist-info/licenses/LICENSE
econfiguration-0.5.3.dist-info/RECORD
