Metadata-Version: 2.1
Name: econfiguration
Version: 0.5.3
Summary: A simple log module
Project-URL: Homepage, https://github.com/numlinka/pylogop
Project-URL: Bug Tracker, https://github.com/numlinka/pylogop/issues
Author-email: numLinka <numlinka@163.com>
License-File: LICENSE
Classifier: License :: OSI Approved :: MIT License
Classifier: Operating System :: OS Independent
Classifier: Programming Language :: Python :: 3
Requires-Python: >=3.7
